moschitta_serialization/__init__.py
moschitta_serialization/base_serializer.py
moschitta_serialization/json_serializer.py
moschitta_serialization/msgpack_serializer.py
moschitta_serialization/protobuf_serializer.py
moschitta_serialization/utils.py
moschitta_serialization/yaml_serializer.py
moschitta_serialization-0.1.1.dist-info/LICENSE
moschitta_serialization-0.1.1.dist-info/METADATA
moschitta_serialization-0.1.1.dist-info/WHEEL
moschitta_serialization-0.1.1.dist-info/entry_points.txt
moschitta_serialization-0.1.1.dist-info/RECORD
