Metadata-Version: 2.1
Name: moschitta-serialization
Version: 0.1.1
Summary: 
Author: Skyler Saville
Author-email: skylersaville@gmail.com
Requires-Python: >=3.11,<4.0
Classifier: Programming Language :: Python :: 3
Classifier: Programming Language :: Python :: 3.11
Requires-Dist: msgpack (>=1.0.8,<2.0.0)
Requires-Dist: protobuf (>=5.26.1,<6.0.0)
Requires-Dist: pyyaml (>=6.0.1,<7.0.0)
